pent/__init__.py
pent/enums.py
pent/errors.py
pent/parser.py
pent/patterns.py
pent/thrulist.py
pent/token.py
pent/utils.py
pent-0.2.dist-info/LICENSE.txt
pent-0.2.dist-info/METADATA
pent-0.2.dist-info/WHEEL
pent-0.2.dist-info/top_level.txt
pent-0.2.dist-info/RECORD
