Metadata-Version: 2.1
Name: pent
Version: 0.2
Summary: pent Extracts Numerical Text
Home-page: https://www.github.com/bskinn/pent
Author: Brian Skinn
Author-email: bskinn@alum.mit.edu
License: MIT License
Platform: UNKNOWN
Classifier: License :: OSI Approved :: MIT License
Classifier: Natural Language :: English
Classifier: Intended Audience :: Science/Research
Classifier: Operating System :: OS Independent
Classifier: Programming Language :: Python :: 3
Classifier: Programming Language :: Python :: 3 :: Only
Classifier: Programming Language :: Python :: 3.5
Classifier: Programming Language :: Python :: 3.6
Classifier: Programming Language :: Python :: 3.7
Classifier: Programming Language :: Python :: 3.8
Classifier: Topic :: Scientific/Engineering
Classifier: Topic :: Scientific/Engineering :: Mathematics
Classifier: Topic :: Utilities
Classifier: Development Status :: 4 - Beta
Requires: attrs (>=17.1)
Requires: pyparsing (>=1.5.5)
Provides: pent
Requires-Python: >=3.4
Requires-Dist: attrs (>=17.1)
Requires-Dist: pyparsing (>=1.5.5)
